slowql/__init__.py
slowql/__main__.py
slowql/analyzers/__init__.py
slowql/analyzers/base.py
slowql/analyzers/registry.py
slowql/analyzers/compliance/__init__.py
slowql/analyzers/cost/__init__.py
slowql/analyzers/performance/__init__.py
slowql/analyzers/quality/__init__.py
slowql/analyzers/reliability/__init__.py
slowql/analyzers/security/__init__.py
slowql/cli/__init__.py
slowql/cli/app.py
slowql/cli/ui/animations.py
slowql/cli/ui/theme.py
slowql/core/__init__.py
slowql/core/config.py
slowql/core/engine.py
slowql/core/exceptions.py
slowql/core/models.py
slowql/parser/__init__.py
slowql/parser/base.py
slowql/parser/tokenizer.py
slowql/parser/universal.py
slowql/parser/ast/nodes.py
slowql/reporters/base.py
slowql/reporters/console.py
slowql/reporters/json_reporter.py
slowql/rules/__init__.py
slowql/rules/base.py
slowql/rules/catalog.py
slowql/rules/registry.py
slowql/utils/io.py
slowql/utils/text.py
slowql-1.3.0.dist-info/METADATA
slowql-1.3.0.dist-info/WHEEL
slowql-1.3.0.dist-info/entry_points.txt
slowql-1.3.0.dist-info/licenses/LICENSE
slowql-1.3.0.dist-info/RECORD
