Metadata-Version: 2.4
Name: slowql
Version: 1.3.0
Summary: Next-generation SQL analyzer: Security, Performance, Compliance, Cost optimization
Project-URL: Homepage, https://github.com/makroumi/slowql
Project-URL: Documentation, https://slowql.dev/docs
Project-URL: Repository, https://github.com/makroumi/slowql
Project-URL: Issues, https://github.com/makroumi/slowql/issues
Project-URL: Changelog, https://github.com/makroumi/slowql/blob/main/CHANGELOG.md
Author-email: makroumi <contact@makroumi.dev>
Maintainer-email: makroumi <contact@makroumi.dev>
License-Expression: Apache-2.0
License-File: LICENSE
Keywords: analyzer,compliance,database,gdpr,hipaa,linter,mysql,optimization,pci-dss,performance,postgresql,security,sql,static-analysis
Classifier: Development Status :: 4 - Beta
Classifier: Environment :: Console
Classifier: Intended Audience :: Developers
Classifier: Intended Audience :: System Administrators
Classifier: License :: OSI Approved :: Apache Software License
Classifier: Operating System :: OS Independent
Classifier: Programming Language :: Python :: 3
Classifier: Programming Language :: Python :: 3.11
Classifier: Programming Language :: Python :: 3.12
Classifier: Programming Language :: Python :: 3.13
Classifier: Programming Language :: SQL
Classifier: Topic :: Database
Classifier: Topic :: Security
Classifier: Topic :: Software Development :: Quality Assurance
Classifier: Topic :: Software Development :: Testing
Classifier: Typing :: Typed
Requires-Python: >=3.11
Requires-Dist: pydantic>=2.6.0
Requires-Dist: rich>=13.7.0
Requires-Dist: sqlglot>=23.0.0
Requires-Dist: tomli>=2.0.0
Requires-Dist: typer>=0.12.0
Provides-Extra: all
Requires-Dist: mkdocs-material>=9.5.0; extra == 'all'
Requires-Dist: mkdocs>=1.5.0; extra == 'all'
Requires-Dist: mkdocstrings[python]>=0.24.0; extra == 'all'
Requires-Dist: mypy>=1.8.0; extra == 'all'
Requires-Dist: pandas>=2.0.0; extra == 'all'
Requires-Dist: pre-commit>=3.6.0; extra == 'all'
Requires-Dist: pytest-asyncio>=0.23.0; extra == 'all'
Requires-Dist: pytest-cov>=4.1.0; extra == 'all'
Requires-Dist: pytest-xdist>=3.5.0; extra == 'all'
Requires-Dist: pytest>=8.0.0; extra == 'all'
Requires-Dist: readchar>=4.0.0; extra == 'all'
Requires-Dist: ruff>=0.3.0; extra == 'all'
Provides-Extra: dev
Requires-Dist: mypy>=1.8.0; extra == 'dev'
Requires-Dist: pandas>=2.0.0; extra == 'dev'
Requires-Dist: pre-commit>=3.6.0; extra == 'dev'
Requires-Dist: pytest-asyncio>=0.23.0; extra == 'dev'
Requires-Dist: pytest-cov>=4.1.0; extra == 'dev'
Requires-Dist: pytest-xdist>=3.5.0; extra == 'dev'
Requires-Dist: pytest>=8.0.0; extra == 'dev'
Requires-Dist: ruff>=0.3.0; extra == 'dev'
Provides-Extra: docs
Requires-Dist: mkdocs-material>=9.5.0; extra == 'docs'
Requires-Dist: mkdocs>=1.5.0; extra == 'docs'
Requires-Dist: mkdocstrings[python]>=0.24.0; extra == 'docs'
Provides-Extra: interactive
Requires-Dist: readchar>=4.0.0; extra == 'interactive'
Provides-Extra: test
Requires-Dist: pandas>=2.0.0; extra == 'test'
Requires-Dist: pytest-asyncio>=0.23.0; extra == 'test'
Requires-Dist: pytest-cov>=4.1.0; extra == 'test'
Requires-Dist: pytest-xdist>=3.5.0; extra == 'test'
Requires-Dist: pytest>=8.0.0; extra == 'test'
